pandas_f/__init__.py
pandas_f-0.0.1.dist-info/LICENSE
pandas_f-0.0.1.dist-info/METADATA
pandas_f-0.0.1.dist-info/WHEEL
pandas_f-0.0.1.dist-info/top_level.txt
pandas_f-0.0.1.dist-info/RECORD
