Metadata-Version: 2.1
Name: pandas-f
Version: 0.0.1
Summary: pandas extension that adds a flatmap
Home-page: http://github.com/dair-targ/pandas_f
Author: Vladimir Berkutov
Author-email: vladimir.berkutov@gmail.com
License: Apache 2.0
Platform: UNKNOWN
Classifier: Development Status :: 3 - Alpha
Classifier: Environment :: Plugins
Classifier: Intended Audience :: Science/Research
Classifier: License :: OSI Approved :: Apache Software License
Classifier: Typing :: Typed
Requires-Python: >=3.6
Requires-Dist: pandas
